visedit/__init__.py
visedit/string_edit.py
visedit/utils/__init__.py
visedit/utils/color_settings.py
visedit/utils/edit_formatter.py
visedit/utils/levenshtein.py
visedit-1.0.5.dist-info/LICENSE
visedit-1.0.5.dist-info/METADATA
visedit-1.0.5.dist-info/WHEEL
visedit-1.0.5.dist-info/top_level.txt
visedit-1.0.5.dist-info/RECORD
